Metadata-Version: 2.1
Name: napari-bbox
Version: 0.0.9
Summary: A new layer for bounding boxes in 2+ dimensions
Home-page: https://github.com/bauerdavid/napari-bbox
Author: David Bauer
Author-email: dbauer@brc.hu
License: BSD-3-Clause
Project-URL: Bug Tracker, https://github.com/bauerdavid/napari-bbox/issues
Project-URL: Documentation, https://github.com/bauerdavid/napari-bbox#README.md
Project-URL: Source Code, https://github.com/bauerdavid/napari-bbox
Project-URL: User Support, https://github.com/bauerdavid/napari-bbox/issues
Classifier: Development Status :: 2 - Pre-Alpha
Classifier: Framework :: napari
Classifier: Intended Audience :: Developers
Classifier: License :: OSI Approved :: BSD License
Classifier: Operating System :: OS Independent
Classifier: Programming Language :: Python
Classifier: Programming Language :: Python :: 3
Classifier: Programming Language :: Python :: 3 :: Only
Classifier: Programming Language :: Python :: 3.9
Classifier: Programming Language :: Python :: 3.10
Classifier: Programming Language :: Python :: 3.11
Classifier: Programming Language :: Python :: 3.12
Classifier: Topic :: Scientific/Engineering :: Image Processing
Requires-Python: >=3.9
License-File: LICENSE
Requires-Dist: numpy
Requires-Dist: qtpy
Requires-Dist: napari>=0.4.15
Requires-Dist: packaging
Requires-Dist: pandas
Requires-Dist: npe2
Requires-Dist: vispy
Provides-Extra: testing
Requires-Dist: tox; extra == "testing"
Requires-Dist: pytest; extra == "testing"
Requires-Dist: pytest-cov; extra == "testing"
Requires-Dist: pytest-qt; extra == "testing"
Requires-Dist: napari; extra == "testing"
Requires-Dist: pyqt5; extra == "testing"
